pfd_toolkit/__init__.py
pfd_toolkit/cleaner.py
pfd_toolkit/config.py
pfd_toolkit/extractor.py
pfd_toolkit/llm.py
pfd_toolkit/loader.py
pfd_toolkit/screener.py
pfd_toolkit/text_utils.py
pfd_toolkit/scraper/__init__.py
pfd_toolkit/scraper/html_extractor.py
pfd_toolkit/scraper/llm_extractor.py
pfd_toolkit/scraper/pdf_extractor.py
pfd_toolkit/scraper/scraper.py
pfd_toolkit-0.3.7.dist-info/METADATA
pfd_toolkit-0.3.7.dist-info/WHEEL
pfd_toolkit-0.3.7.dist-info/licenses/LICENCE
pfd_toolkit-0.3.7.dist-info/RECORD
