Metadata-Version: 2.4
Name: pfd_toolkit
Version: 0.3.7
Summary: A toolkit for using Prevention of Future Death (PFD) Reports for Research and Policy Projects.
Project-URL: Homepage, https://github.com/Sam-Osian/PFD-toolkit
Project-URL: Issues, https://github.com/Sam-Osian/PFD-toolkit/issues
Author-email: Sam Osian <samoand@liverpool.ac.uk>, Jonathan Pytches <jonathan.pytches@gmail.com>
License-Expression: AGPL-3.0-or-later
License-File: LICENCE
Classifier: License :: OSI Approved :: GNU Affero General Public License v3 or later (AGPLv3+)
Classifier: Operating System :: OS Independent
Classifier: Programming Language :: Python :: 3
Classifier: Programming Language :: Python :: 3.10
Classifier: Programming Language :: Python :: 3.11
Classifier: Programming Language :: Python :: 3.12
Classifier: Programming Language :: Python :: 3.13
Requires-Python: >=3.10
Requires-Dist: adjusttext>=1.3.0
Requires-Dist: backoff>=2.2.1
Requires-Dist: beautifulsoup4>=4.13.4
Requires-Dist: dotenv>=0.9.9
Requires-Dist: httpx>=0.28.1
Requires-Dist: openai>=1.88.0
Requires-Dist: pandas<2.2.3,>=2.2.2; python_version < '3.13'
Requires-Dist: pandas>=2.2.3; python_version >= '3.13'
Requires-Dist: pydantic>=2.11.7
Requires-Dist: pymupdf>=1.26.1
Requires-Dist: python-dateutil>=2.9.0.post0
Requires-Dist: requests>=2.32.3
Requires-Dist: tiktoken>=0.9.0
Requires-Dist: tqdm>=4.67.1
